.DS_Store
lattice_mc/__init__.py
lattice_mc/atom.py
lattice_mc/cluster.py
lattice_mc/error.py
lattice_mc/global_vars.py
lattice_mc/init_lattice.py
lattice_mc/jump.py
lattice_mc/lattice.py
lattice_mc/lattice_site.py
lattice_mc/lookup_table.py
lattice_mc/options.py
lattice_mc/simulation.py
lattice_mc/species.py
lattice_mc/transitions.py
lattice_mc-1.0.4.dist-info/METADATA
lattice_mc-1.0.4.dist-info/RECORD
lattice_mc-1.0.4.dist-info/WHEEL
lattice_mc-1.0.4.dist-info/top_level.txt
