Metadata-Version: 2.1
Name: lattice-mc
Version: 1.0.4
Summary: A lattice-gas Monte-Carlo simulation tool
Home-page: https://github.com/bjmorgan/lattice_mc
Author: Benjamin J. Morgan
Author-email: b.j.morgan@bath.ac.uk
License: MIT
Download-URL: https://github.com/bjmorgan/lattice_mc/archive/1.0.4.tar.gz
Platform: UNKNOWN
Requires-Dist: numpy
Requires-Dist: matplotlib
Requires-Dist: pandas
Requires-Dist: scipy
Requires-Dist: coverage (==4.3.4)
Requires-Dist: codeclimate-test-reporter
